cfxplorer/__init__.py
cfxplorer/focus.py
cfxplorer/utils.py
cfxplorer/version.py
cfxplorer/tests/__init__.py
cfxplorer/tests/test_focus.py
cfxplorer/tests/test_utils.py
CFXplorer-0.1.0.dist-info/LICENSE
CFXplorer-0.1.0.dist-info/METADATA
CFXplorer-0.1.0.dist-info/WHEEL
CFXplorer-0.1.0.dist-info/top_level.txt
CFXplorer-0.1.0.dist-info/RECORD
