Metadata-Version: 2.1
Name: CFXplorer
Version: 0.1.0
Summary: CFXplorer is a python package for generating counterfactual explanations for given model and feature set
Author: Kyosuke Morita
Author-email: kq441morita@gmail.com
Keywords: python,counterfactual explanation,binary classification,machine learning
Classifier: Development Status :: 3 - Alpha
Classifier: Intended Audience :: Education
Classifier: Intended Audience :: Science/Research
Classifier: Intended Audience :: Developers
Classifier: Intended Audience :: Information Technology
Classifier: License :: OSI Approved :: BSD License
Classifier: Programming Language :: Python :: 3
Classifier: Operating System :: MacOS :: MacOS X
Classifier: Operating System :: Microsoft :: Windows
License-File: LICENSE
